{"pages": [{"class_name": "LoginPage", "file_name": "login_page.py", "locators": {"email_field": "//input[@id='email']", "password_field": "//input[@id='password']", "login_button": "//button[@id='login']", "error_message": "//div[@class='error-message']", "user_name_header": "//div[@id='user-header']"}, "actions": ["navigate_to_login_page", "enter_email", "enter_password", "click_login_button"], "validations": ["is_login_page_displayed", "is_email_accepted", "is_password_masked", "is_error_message_displayed", "is_user_authenticated", "is_user_name_displayed", "is_session_token_generated", "is_user_on_login_page"]}, {"class_name": "DashboardPage", "file_name": "dashboard_page.py", "locators": {"user_name_header": "//div[@id='user-header']"}, "actions": ["verify_user_session"], "validations": ["is_dashboard_displayed", "is_user_name_displayed"]}]}